MANIFEST.in
README
README.md
setup.py
scripts/whack
whack/__init__.py
whack/args.py
whack/builder.py
whack/caching.py
whack/cli.py
whack/common.py
whack/deployer.py
whack/downloads.py
whack/env.py
whack/errors.py
whack/files.py
whack/hashes.py
whack/indices.py
whack/local.py
whack/operations.py
whack/packagerequests.py
whack/platform.py
whack/providers.py
whack/slugs.py
whack/sources.py
whack/tarballs.py
whack/tempdir.py
whack/testing.py
whack/uris.py
whack.egg-info/PKG-INFO
whack.egg-info/SOURCES.txt
whack.egg-info/dependency_links.txt
whack.egg-info/requires.txt
whack.egg-info/top_level.txt