Metadata-Version: 1.0
Name: whack
Version: 0.7.0
Summary: Utility for installing binaries from source with a single command
Home-page: http://github.com/mwilliamson/whack
Author: Michael Williamson
Author-email: UNKNOWN
License: UNKNOWN
Platform: UNKNOWN
